{
    "studentID": [
        {
            "position": [
                480,
                410,
                580,
                530
            ],
            "label": "id"
        },
        {
            "position": [
                610,
                410,
                710,
                530
            ],
            "label": "id"
        },
        {
            "position": [
                740,
                410,
                840,
                530
            ],
            "label": "id"
        },
        {
            "position": [
                870,
                410,
                970,
                530
            ],
            "label": "id"
        },
        {
            "position": [
                1000,
                410,
                1100,
                530
            ],
            "label": "id"
        },
        {
            "position": [
                1130,
                410,
                1230,
                530
            ],
            "label": "id"
        },
        {
            "position": [
                1260,
                410,
                1360,
                530
            ],
            "label": "id"
        },
        {
            "position": [
                1390,
                410,
                1490,
                530
            ],
            "label": "id"
        },
        {
            "position": [
                1520,
                410,
                1620,
                530
            ],
            "label": "id"
        },
        {
            "position": [
                1650,
                410,
                1750,
                530
            ],
            "label": "id"
        },
        {
            "position": [
                1780,
                410,
                1880,
                530
            ],
            "label": "id"
        },
        {
            "position": [
                1910,
                410,
                2010,
                530
            ],
            "label": "id"
        },
        {
            "position": [
                2040,
                410,
                2140,
                530
            ],
            "label": "id"
        }
    ],
    "1": {
        "position": [
            310,
            840,
            410,
            960
        ],
        "label": "number"
    },
    "2": {
        "position": [
            660,
            840,
            760,
            960
        ],
        "label": "number"
    },
    "3": {
        "position": [
            1010,
            840,
            1110,
            960
        ],
        "label": "number"
    },
    "4": {
        "position": [
            1360,
            840,
            1460,
            960
        ],
        "label": "number"
    },
    "5": {
        "position": [
            1710,
            840,
            1810,
            960
        ],
        "label": "number"
    },
    "6": {
        "label": "line"
    },
    "7": {
        "label": "line"
    }
}